{
    "background": "dark",
    "classes": [
        "P.aeruginosa"
    ],
    "colonies_number": 68,
    "labels": [
        {
            "class": "P.aeruginosa",
            "height": 88,
            "id": 1,
            "width": 88,
            "x": 429,
            "y": 2188
        },
        {
            "class": "P.aeruginosa",
            "height": 129,
            "id": 2,
            "width": 129,
            "x": 659,
            "y": 2118
        },
        {
            "class": "P.aeruginosa",
            "height": 45,
            "id": 3,
            "width": 45,
            "x": 1133,
            "y": 2118
        },
        {
            "class": "P.aeruginosa",
            "height": 129,
            "id": 4,
            "width": 129,
            "x": 739,
            "y": 1877
        },
        {
            "class": "P.aeruginosa",
            "height": 117,
            "id": 5,
            "width": 117,
            "x": 772,
            "y": 1960
        },
        {
            "class": "P.aeruginosa",
            "height": 156,
            "id": 6,
            "width": 156,
            "x": 840,
            "y": 1775
        },
        {
            "class": "P.aeruginosa",
            "height": 141,
            "id": 7,
            "width": 141,
            "x": 783,
            "y": 1647
        },
        {
            "class": "P.aeruginosa",
            "height": 106,
            "id": 8,
            "width": 106,
            "x": 529,
            "y": 1644
        },
        {
            "class": "P.aeruginosa",
            "height": 88,
            "id": 9,
            "width": 88,
            "x": 431,
            "y": 1437
        },
        {
            "class": "P.aeruginosa",
            "height": 117,
            "id": 10,
            "width": 117,
            "x": 452,
            "y": 1506
        },
        {
            "class": "P.aeruginosa",
            "height": 117,
            "id": 11,
            "width": 117,
            "x": 563,
            "y": 1372
        },
        {
            "class": "P.aeruginosa",
            "height": 129,
            "id": 12,
            "width": 129,
            "x": 690,
            "y": 1359
        },
        {
            "class": "P.aeruginosa",
            "height": 96,
            "id": 13,
            "width": 96,
            "x": 594,
            "y": 1055
        },
        {
            "class": "P.aeruginosa",
            "height": 80,
            "id": 14,
            "width": 80,
            "x": 834,
            "y": 983
        },
        {
            "class": "P.aeruginosa",
            "height": 55,
            "id": 15,
            "width": 88,
            "x": 987,
            "y": 697
        },
        {
            "class": "P.aeruginosa",
            "height": 117,
            "id": 16,
            "width": 89,
            "x": 959,
            "y": 805
        },
        {
            "class": "P.aeruginosa",
            "height": 106,
            "id": 17,
            "width": 88,
            "x": 1011,
            "y": 838
        },
        {
            "class": "P.aeruginosa",
            "height": 96,
            "id": 18,
            "width": 96,
            "x": 1416,
            "y": 681
        },
        {
            "class": "P.aeruginosa",
            "height": 106,
            "id": 19,
            "width": 106,
            "x": 1268,
            "y": 1418
        },
        {
            "class": "P.aeruginosa",
            "height": 88,
            "id": 20,
            "width": 88,
            "x": 1363,
            "y": 1273
        },
        {
            "class": "P.aeruginosa",
            "height": 106,
            "id": 21,
            "width": 106,
            "x": 1567,
            "y": 1388
        },
        {
            "class": "P.aeruginosa",
            "height": 156,
            "id": 22,
            "width": 156,
            "x": 1193,
            "y": 1733
        },
        {
            "class": "P.aeruginosa",
            "height": 141,
            "id": 23,
            "width": 141,
            "x": 1370,
            "y": 2098
        },
        {
            "class": "P.aeruginosa",
            "height": 117,
            "id": 24,
            "width": 117,
            "x": 1538,
            "y": 2011
        },
        {
            "class": "P.aeruginosa",
            "height": 129,
            "id": 25,
            "width": 129,
            "x": 1343,
            "y": 2299
        },
        {
            "class": "P.aeruginosa",
            "height": 141,
            "id": 26,
            "width": 141,
            "x": 1000,
            "y": 2530
        },
        {
            "class": "P.aeruginosa",
            "height": 80,
            "id": 27,
            "width": 80,
            "x": 680,
            "y": 2642
        },
        {
            "class": "P.aeruginosa",
            "height": 141,
            "id": 28,
            "width": 141,
            "x": 927,
            "y": 2982
        },
        {
            "class": "P.aeruginosa",
            "height": 96,
            "id": 29,
            "width": 96,
            "x": 1298,
            "y": 2917
        },
        {
            "class": "P.aeruginosa",
            "height": 117,
            "id": 30,
            "width": 117,
            "x": 1622,
            "y": 3246
        },
        {
            "class": "P.aeruginosa",
            "height": 80,
            "id": 31,
            "width": 80,
            "x": 1848,
            "y": 3367
        },
        {
            "class": "P.aeruginosa",
            "height": 88,
            "id": 32,
            "width": 88,
            "x": 1853,
            "y": 3061
        },
        {
            "class": "P.aeruginosa",
            "height": 96,
            "id": 33,
            "width": 96,
            "x": 1677,
            "y": 2642
        },
        {
            "class": "P.aeruginosa",
            "height": 96,
            "id": 34,
            "width": 96,
            "x": 1688,
            "y": 2412
        },
        {
            "class": "P.aeruginosa",
            "height": 60,
            "id": 35,
            "width": 60,
            "x": 2619,
            "y": 2817
        },
        {
            "class": "P.aeruginosa",
            "height": 106,
            "id": 36,
            "width": 96,
            "x": 2507,
            "y": 2808
        },
        {
            "class": "P.aeruginosa",
            "height": 80,
            "id": 37,
            "width": 80,
            "x": 2869,
            "y": 2857
        },
        {
            "class": "P.aeruginosa",
            "height": 54,
            "id": 38,
            "width": 54,
            "x": 2985,
            "y": 2594
        },
        {
            "class": "P.aeruginosa",
            "height": 117,
            "id": 39,
            "width": 117,
            "x": 2698,
            "y": 2347
        },
        {
            "class": "P.aeruginosa",
            "height": 106,
            "id": 40,
            "width": 105,
            "x": 2353,
            "y": 2310
        },
        {
            "class": "P.aeruginosa",
            "height": 106,
            "id": 41,
            "width": 106,
            "x": 2327,
            "y": 2374
        },
        {
            "class": "P.aeruginosa",
            "height": 96,
            "id": 42,
            "width": 96,
            "x": 2141,
            "y": 2207
        },
        {
            "class": "P.aeruginosa",
            "height": 88,
            "id": 43,
            "width": 88,
            "x": 2029,
            "y": 2069
        },
        {
            "class": "P.aeruginosa",
            "height": 96,
            "id": 44,
            "width": 96,
            "x": 1748,
            "y": 2162
        },
        {
            "class": "P.aeruginosa",
            "height": 88,
            "id": 45,
            "width": 88,
            "x": 2100,
            "y": 1938
        },
        {
            "class": "P.aeruginosa",
            "height": 88,
            "id": 46,
            "width": 88,
            "x": 2179,
            "y": 1967
        },
        {
            "class": "P.aeruginosa",
            "height": 72,
            "id": 47,
            "width": 72,
            "x": 2936,
            "y": 1910
        },
        {
            "class": "P.aeruginosa",
            "height": 117,
            "id": 48,
            "width": 117,
            "x": 2507,
            "y": 1579
        },
        {
            "class": "P.aeruginosa",
            "height": 106,
            "id": 49,
            "width": 106,
            "x": 2592,
            "y": 1561
        },
        {
            "class": "P.aeruginosa",
            "height": 72,
            "id": 50,
            "width": 72,
            "x": 2834,
            "y": 1518
        },
        {
            "class": "P.aeruginosa",
            "height": 66,
            "id": 51,
            "width": 87,
            "x": 2053,
            "y": 1289
        },
        {
            "class": "P.aeruginosa",
            "height": 96,
            "id": 52,
            "width": 96,
            "x": 2040,
            "y": 1345
        },
        {
            "class": "P.aeruginosa",
            "height": 80,
            "id": 53,
            "width": 80,
            "x": 1742,
            "y": 1134
        },
        {
            "class": "P.aeruginosa",
            "height": 80,
            "id": 54,
            "width": 80,
            "x": 1775,
            "y": 1188
        },
        {
            "class": "P.aeruginosa",
            "height": 88,
            "id": 55,
            "width": 88,
            "x": 1753,
            "y": 1275
        },
        {
            "class": "P.aeruginosa",
            "height": 106,
            "id": 56,
            "width": 106,
            "x": 1897,
            "y": 1089
        },
        {
            "class": "P.aeruginosa",
            "height": 96,
            "id": 57,
            "width": 96,
            "x": 1744,
            "y": 968
        },
        {
            "class": "P.aeruginosa",
            "height": 96,
            "id": 58,
            "width": 85,
            "x": 1912,
            "y": 903
        },
        {
            "class": "P.aeruginosa",
            "height": 80,
            "id": 59,
            "width": 80,
            "x": 1976,
            "y": 915
        },
        {
            "class": "P.aeruginosa",
            "height": 96,
            "id": 60,
            "width": 96,
            "x": 1897,
            "y": 722
        },
        {
            "class": "P.aeruginosa",
            "height": 96,
            "id": 61,
            "width": 96,
            "x": 2053,
            "y": 669
        },
        {
            "class": "P.aeruginosa",
            "height": 96,
            "id": 62,
            "width": 96,
            "x": 2438,
            "y": 868
        },
        {
            "class": "P.aeruginosa",
            "height": 88,
            "id": 63,
            "width": 88,
            "x": 2423,
            "y": 735
        },
        {
            "class": "P.aeruginosa",
            "height": 106,
            "id": 64,
            "width": 106,
            "x": 2366,
            "y": 898
        },
        {
            "class": "P.aeruginosa",
            "height": 106,
            "id": 65,
            "width": 106,
            "x": 2238,
            "y": 982
        },
        {
            "class": "P.aeruginosa",
            "height": 117,
            "id": 66,
            "width": 117,
            "x": 2435,
            "y": 1099
        },
        {
            "class": "P.aeruginosa",
            "height": 66,
            "id": 67,
            "width": 66,
            "x": 2733,
            "y": 961
        },
        {
            "class": "P.aeruginosa",
            "height": 80,
            "id": 68,
            "width": 80,
            "x": 2745,
            "y": 1089
        }
    ],
    "sample_id": 3263
}